anonyspark/__init__.py
anonyspark/cli.py
anonyspark/masking.py
anonyspark/utils.py
tests/__init__.py
tests/test_masking.py
tests/test_schema_masking.py
anonyspark_core-0.1.0.dist-info/METADATA
anonyspark_core-0.1.0.dist-info/WHEEL
anonyspark_core-0.1.0.dist-info/top_level.txt
anonyspark_core-0.1.0.dist-info/RECORD
