Metadata-Version: 2.4
Name: anonyspark-core
Version: 0.1.0
Summary: Schema-driven data masking and anonymization for PySpark DataFrames
Home-page: https://github.com/yourusername/anonyspark
Author: Naga Adithya Kaushik
Author-email: Naga Adithya Kaushik <adithyakaushikch@gmail.com>
License: MIT-License
Classifier: Programming Language :: Python :: 3
Classifier: License :: OSI Approved :: Apache Software License
Classifier: Operating System :: OS Independent
Requires-Python: >=3.7
Dynamic: requires-python
